{
  "name": "ChicDead26's Packages",
  "packages": [
    {
      "name": "Super Metroid Map Rando",
      "game_name": "Super Metroid",
      "author": "ChicDead26, SauceRelic",
      "version": "1.5.2.0",
      "flags": [ "chathud, autotracker" ],
      "uid": "sm_maprando_chicdead26",
      "link": "https://chicdead26.github.io/Super-Metroid-Map-Rando-Tracker/sm_maprando_chicdead26.zip",
      "variants": [
        {
          "name": "Full Tracker",
          "flags": [ "chathud, autotracker" ]
        },
        {
          "name": "Objective: Bosses",
          "flags": [ "chathud, autotracker" ]
        },
        {
          "name": "Objective: Minibosses",
          "flags": [ "chathud, autotracker" ]
        },
        {
          "name": "Objective: Metroids",
          "flags": [ "chathud, autotracker" ]
        },
        {
          "name": "Objective: Chozos",
          "flags": [ "chathud, autotracker" ]
        },
        {
          "name": "Objective: Pirates",
          "flags": [ "chathud, autotracker" ]
        },
        {
          "name": "Objective: None",
          "flags": [ "chathud, autotracker" ]
        }
      ]
    }
  ]
}
